queryshield_cli/__init__.py
queryshield_cli/main.py
queryshield_cli/production_monitor.py
queryshield-0.3.0.dist-info/METADATA
queryshield-0.3.0.dist-info/WHEEL
queryshield-0.3.0.dist-info/entry_points.txt
queryshield-0.3.0.dist-info/RECORD
