Metadata-Version: 2.4
Name: queryshield
Version: 0.3.0
Summary: CLI for QueryShield
Author-email: QueryShield <dev@queryshield.io>
Requires-Python: >=3.9
Requires-Dist: httpx>=0.24.0
Requires-Dist: rich>=13.0
Requires-Dist: typer>=0.12
